smartthings_rest/__init__.py
smartthings_rest-0.1.2.dist-info/LICENSE
smartthings_rest-0.1.2.dist-info/WHEEL
smartthings_rest-0.1.2.dist-info/METADATA
smartthings_rest-0.1.2.dist-info/RECORD
