Metadata-Version: 2.1
Name: smartthings-rest
Version: 0.1.2
Summary: Smart and straightforward lib for controlling things with smartthings
Home-page: https://github.com/viktorfreiman/smartthings-rest
License: MIT
Author: Viktor Freiman
Author-email: freiman.viktor@gmail.com
Requires-Python: >=3.6.2,<4.0.0
Classifier: License :: OSI Approved :: MIT License
Classifier: Programming Language :: Python :: 3
Classifier: Programming Language :: Python :: 3.10
Classifier: Programming Language :: Python :: 3.7
Classifier: Programming Language :: Python :: 3.8
Classifier: Programming Language :: Python :: 3.9
Requires-Dist: requests (>=2.26.0,<3.0.0)
Project-URL: Documentation, https://smartthings-rest.readthedocs.io
Project-URL: Repository, https://github.com/viktorfreiman/smartthings-rest
